MANIFEST.in
README.rst
setup.py
yconf/__init__.py
yconf/config.py
yconf/util.py
yconf.egg-info/PKG-INFO
yconf.egg-info/SOURCES.txt
yconf.egg-info/dependency_links.txt
yconf.egg-info/requires.txt
yconf.egg-info/top_level.txt
yconf/tests/__init__.py
yconf/tests/test_config.py
yconf/tests/test_parser.py
yconf/tests/test_util.py