Metadata-Version: 1.1
Name: yconf
Version: 0.4
Summary: Wrapper that combines argparse with yaml config files.
Home-page: https://github.com/kampka/yconf
Author: Christian Kampka
Author-email: christian@kampka.net
License: BSD-3
Platform: UNKNOWN
Classifier: Development Status :: 5 - Production/Stable
Classifier: Intended Audience :: Developers
Classifier: License :: OSI Approved :: BSD License
Classifier: Operating System :: OS Independent
Classifier: Programming Language :: Python
Classifier: Programming Language :: Python :: 3
Classifier: Topic :: Software Development
